LICENSE
MANIFEST.in
README.rst
setup.cfg
setup.py
_res/__init__.py
_res/testbatch_ids.py
batchpy/__init__.py
batchpy/__version__.py
batchpy/batch.py
batchpy/run.py
batchpy.egg-info/PKG-INFO
batchpy.egg-info/SOURCES.txt
batchpy.egg-info/dependency_links.txt
batchpy.egg-info/requires.txt
batchpy.egg-info/top_level.txt
tests/__init__.py
tests/common.py
tests/test.py
tests/test_batch.py
tests/test_doc.py
tests/test_interrupt.py
tests/test_run.py
tests/test_various.py