Metadata-Version: 1.1
Name: batchpy
Version: 1.2.2
Summary: A package to efficiently run batches of similar calculations
Home-page: https://github.com/BrechtBa/batchpy
Author: Brecht Baeten
Author-email: brecht.baeten@gmail.com
License: GPLv3
Platform: UNKNOWN
Classifier: Programming Language :: Python :: 2.7
